enablebanking/__init__.py
enablebanking/api_client.py
enablebanking/configuration.py
enablebanking/api/__init__.py
enablebanking/api/aisp_api.py
enablebanking/api/auth_api.py
enablebanking/api/meta_api.py
enablebanking/api/pisp_api.py
enablebanking/eb/__init__.py
enablebanking/eb/broker_platform.py
enablebanking/eb/exception.py
enablebanking/eb/platform.py
enablebanking/models/__init__.py
enablebanking/models/access.py
enablebanking/models/account_identification.py
enablebanking/models/account_links.py
enablebanking/models/account_resource.py
enablebanking/models/accounts_links.py
enablebanking/models/address_type.py
enablebanking/models/aktia_connector_settings.py
enablebanking/models/alandsbanken_connector_settings.py
enablebanking/models/alior_connector_settings.py
enablebanking/models/alm_brand_connector_settings.py
enablebanking/models/amount_type.py
enablebanking/models/auth.py
enablebanking/models/auth_info.py
enablebanking/models/auth_redirect.py
enablebanking/models/authentication_approach.py
enablebanking/models/balance_resource.py
enablebanking/models/balance_status.py
enablebanking/models/balances_access.py
enablebanking/models/balances_links.py
enablebanking/models/bank_transaction_code.py
enablebanking/models/beneficiaries_links.py
enablebanking/models/beneficiary.py
enablebanking/models/bib_connector_settings.py
enablebanking/models/bnp_paribas_poland_connector_settings.py
enablebanking/models/booking_information.py
enablebanking/models/category_purpose_code.py
enablebanking/models/charge_bearer_code.py
enablebanking/models/citadele_connector_settings.py
enablebanking/models/clearing_system_member_identification.py
enablebanking/models/client_info.py
enablebanking/models/connector.py
enablebanking/models/connector_settings.py
enablebanking/models/connectors_links.py
enablebanking/models/consent.py
enablebanking/models/consent_links.py
enablebanking/models/coop_pank_connector_settings.py
enablebanking/models/country_auth_info.py
enablebanking_api-0.5.1.dist-info/METADATA
enablebanking_api-0.5.1.dist-info/WHEEL
enablebanking_api-0.5.1.dist-info/top_level.txt
enablebanking_api-0.5.1.dist-info/RECORD
