Metadata-Version: 2.1
Name: enablebanking-api
Version: 0.5.1
Summary: Single Python interface for many Open Banking / PSD2 APIs
Home-page: UNKNOWN
Author-email: hello@enablebanking.com
License: UNKNOWN
Keywords: enable:Banking SDK,Open Banking,PSD2,API aggregation
Platform: UNKNOWN
Classifier: Environment :: Web Environment
Classifier: Intended Audience :: Developers
Classifier: Intended Audience :: Financial and Insurance Industry
Classifier: License :: Other/Proprietary License
Classifier: Operating System :: OS Independent
Classifier: Programming Language :: Python :: 3
Classifier: Programming Language :: Python :: 3 :: Only
Classifier: Topic :: Software Development :: Libraries
Requires-Python: >=3.4
Requires-Dist: certifi
Requires-Dist: python-dateutil
Requires-Dist: cryptography (==2.6.1)
